django_prosemirror/__init__.py
django_prosemirror/apps.py
django_prosemirror/config.py
django_prosemirror/constants.py
django_prosemirror/exceptions.py
django_prosemirror/fields.py
django_prosemirror/py.typed
django_prosemirror/serde.py
django_prosemirror/urls.py
django_prosemirror/widgets.py
django_prosemirror/forms/__init__.py
django_prosemirror/forms/filer.py
django_prosemirror/schema/__init__.py
django_prosemirror/schema/base.py
django_prosemirror/schema/types.py
django_prosemirror/schema/marks/__init__.py
django_prosemirror/schema/marks/code.py
django_prosemirror/schema/marks/italic.py
django_prosemirror/schema/marks/link.py
django_prosemirror/schema/marks/strikethrough.py
django_prosemirror/schema/marks/strong.py
django_prosemirror/schema/marks/underline.py
django_prosemirror/schema/nodes/__init__.py
django_prosemirror/schema/nodes/blockquote.py
django_prosemirror/schema/nodes/bullet_list.py
django_prosemirror/schema/nodes/code_block.py
django_prosemirror/schema/nodes/filer_image.py
django_prosemirror/schema/nodes/hard_break.py
django_prosemirror/schema/nodes/heading.py
django_prosemirror/schema/nodes/horizontal_rule.py
django_prosemirror/schema/nodes/list_item.py
django_prosemirror/schema/nodes/ordered_list.py
django_prosemirror/schema/nodes/paragraph.py
django_prosemirror/schema/nodes/table.py
django_prosemirror/schema/nodes/table_cell.py
django_prosemirror/schema/nodes/table_header.py
django_prosemirror/schema/nodes/table_row.py
django_prosemirror/static/css/django-prosemirror.css
django_prosemirror/static/js/django-prosemirror.js
django_prosemirror/templates/widget.html
django_prosemirror/templatetags/django_prosemirror.py
django_prosemirror/views/__init__.py
django_prosemirror/views/filer_image.py
maykin_django_prosemirror-0.2.0.dist-info/licenses/LICENSE
maykin_django_prosemirror-0.2.0.dist-info/METADATA
maykin_django_prosemirror-0.2.0.dist-info/WHEEL
maykin_django_prosemirror-0.2.0.dist-info/top_level.txt
maykin_django_prosemirror-0.2.0.dist-info/RECORD
