Metadata-Version: 2.4
Name: maykin-django-prosemirror
Version: 0.2.0
Summary: Rich-text fields for Django using Prosemirror - a powerful, schema-driven rich text editor.
Author-email: Maykin Media <support@maykinmedia.nl>
License: Copyright 2025 Maykin Media
Project-URL: Homepage, https://github.com/maykinmedia/django-prosemirror
Project-URL: Documentation, http://django-prosemirror.readthedocs.io/en/latest/
Project-URL: Bug Tracker, https://github.com/maykinmedia/django-prosemirror/issues
Project-URL: Source Code, https://github.com/maykinmedia/django-prosemirror
Keywords: Django,Prosemirror,rich-text,editor,document,JSON,WYSIWYG,content editor,text editor,markdown,html
Classifier: Development Status :: 3 - Alpha
Classifier: Framework :: Django
Classifier: Framework :: Django :: 4.2
Classifier: Framework :: Django :: 5.2
Classifier: Intended Audience :: Developers
Classifier: Operating System :: Unix
Classifier: Operating System :: MacOS
Classifier: Operating System :: Microsoft :: Windows
Classifier: Programming Language :: Python :: 3.11
Classifier: Programming Language :: Python :: 3.12
Classifier: Programming Language :: Python :: 3.13
Classifier: Topic :: Software Development :: Libraries :: Python Modules
Requires-Python: >=3.11
License-File: LICENSE
Requires-Dist: django>=4.2
Requires-Dist: prosemirror>=0.5.2
Provides-Extra: tests
Requires-Dist: pytest-playwright; extra == "tests"
Requires-Dist: pytest-django; extra == "tests"
Requires-Dist: pytest-cov; extra == "tests"
Requires-Dist: tox; extra == "tests"
Requires-Dist: ruff; extra == "tests"
Provides-Extra: images
Requires-Dist: django-filer; extra == "images"
Provides-Extra: docs
Requires-Dist: sphinx; extra == "docs"
Requires-Dist: sphinx-rtd-theme; extra == "docs"
Provides-Extra: release
Requires-Dist: bump-my-version; extra == "release"
Dynamic: license-file
